openledger/__init__.py
openledger/ai/__init__.py
openledger/ai/client.py
openledger/ai/raw_client.py
openledger/authentication/__init__.py
openledger/authentication/client.py
openledger/authentication/raw_client.py
openledger/banks/__init__.py
openledger/banks/client.py
openledger/banks/raw_client.py
openledger/client.py
openledger/core/__init__.py
openledger/core/api_error.py
openledger/core/client_wrapper.py
openledger/core/datetime_utils.py
openledger/core/file.py
openledger/core/http_client.py
openledger/core/http_response.py
openledger/core/jsonable_encoder.py
openledger/core/pydantic_utilities.py
openledger/core/query_encoder.py
openledger/core/remove_none_from_dict.py
openledger/core/request_options.py
openledger/core/serialization.py
openledger/entities/__init__.py
openledger/entities/client.py
openledger/entities/raw_client.py
openledger/entities/types/__init__.py
openledger/entities/types/delete_entities_response.py
openledger/entities/types/entity_create_request_entity_type.py
openledger/entities/types/entity_create_request_status.py
openledger/entities/types/entity_update_request_entity_type.py
openledger/entities/types/entity_update_request_status.py
openledger/entities/types/get_entities_response.py
openledger/entities/types/post_entities_response.py
openledger/entities/types/put_entities_response.py
openledger/environment.py
openledger/errors/__init__.py
openledger/errors/bad_request_error.py
openledger/errors/internal_server_error.py
openledger/errors/not_found_error.py
openledger/integrations/__init__.py
openledger/integrations/client.py
openledger/integrations/raw_client.py
openledger/integrations/types/__init__.py
openledger/integrations/types/post_integrations_connect_response.py
openledger/integrations/types/post_integrations_disconnect_response.py
openledger/py.typed
openledger/reports/__init__.py
openledger/reports/client.py
openledger/reports/raw_client.py
openledger/reports/types/__init__.py
openledger_python_sdk-0.0.46.dist-info/METADATA
openledger_python_sdk-0.0.46.dist-info/WHEEL
openledger_python_sdk-0.0.46.dist-info/RECORD
